{
  "id": "13c151ef",
  "slug": "piera-felina",
  "name": "Associació Piera Felina",
  "shortName": "Piera Felina",
  "animalFocus": "cats",
  "region": "anoia",
  "province": "barcelona",
  "municipalityInscription": "Piera",
  "municipality": "Piera",
  "contactEmail": "aspierafelina@gmail.com",
  "description": "Som un grup d'amants dels animals, que pretén visibilitzar, dotar de mitjans i emparar la feina que desenes de voluntaris fa diàriament, tenint cura dels gats sense llar.",
  "isActive": true,
  "isMunicipal": false,
  "lastUpdate": "2025-10-12T00:00:00.000Z",
  "associativeInscriptionNumber": "72303",
  "dateOfInscription": "2022-12-18T00:00:00.000Z",
  "adoptAnimalsURL": "https://www.instagram.com/piera.felina/",
  "socials": [
    {
      "type": "instagram",
      "url": "https://www.instagram.com/piera.felina/"
    },
    {
      "type": "facebook",
      "url": "https://www.facebook.com/profile.php?id=61572117772004"
    }
  ],
  "sitemap": {
    "lastmod": "2025-10-12T00:00:00.000Z",
    "changefreq": "monthly",
    "priority": 0.5
  }
}