{
  "id": "785d1a22",
  "slug": "progat-terrassa",
  "name": "Associació Progat Terrassa",
  "shortName": "Progat Terrassa",
  "contactEmail": "info@progatterrassa.org",
  "animalFocus": "cats",
  "region": "valles-occidental",
  "province": "barcelona",
  "municipalityInscription": "Terrassa",
  "municipality": "Terrassa",
  "description": "Progat Terrassa és una associació de persones sense ànim de lucre, que treballa per assolir el benestar dels gats del carrer. Els nostres objectius principals: - Gestionar colònies de gats proporcionant vigilància i assistència diària. - Protegir el gat urbà a través de controls sanitaris, esterilització, desparasitació i alimentació. - Estendre el respecte pels gats urbans i involucrar les administracions en les idees de protecció. Ens ajudes?",
  "isActive": true,
  "isMunicipal": false,
  "lastUpdate": "2025-02-25T00:00:00.000Z",
  "logo": "https://d1kvlp4er3agpe.cloudfront.net/resources/images/groups/3/9/2/3/0/9kqpcnyfxd.jpg",
  "website": "https://progatterrassa.org/",
  "adoptAnimalsURL": "https://www.instagram.com/progatterrassa/",
  "associativeInscriptionNumber": "29236",
  "dateOfInscription": "2004-06-22:00:00.000Z",
  "socials": [
    {
      "type": "instagram",
      "url": "https://www.instagram.com/progatterrassa/"
    },
    {
      "type": "facebook",
      "url": "https://www.facebook.com/progat.terrassa1/"
    }
  ]
}