{
  "id": "dcd87b37",
  "slug": "protectora-animals-osona",
  "name": "Associació i Defensa dels Animals d'Osona",
  "shortName": "Protectora d'Animals d'Osona",
  "logo": "https://d1kvlp4er3agpe.cloudfront.net/resources/images/groups/1/7/8/0/0/ekiwtscfcu.jpeg",
  "contactEmail": "infoproteosona@gmail.com",
  "contactPhone": "638986301",
  "contactPhone2": "696256120",
  "region": "osona",
  "province": "barcelona",
  "description": "Vam néixer fa uns trenta anys i sempre hem tingut l’objectiu de salvar els animals. Actualment tenim uns dos-cents gossos i uns cinquanta gats esperant una família: anima’t i vine a conèixer-los! El nostre objectiu principal és donar una vida digne i sana a tots els animals que ho necessiten . Per això, intentem generar recursos per garantir una atenció adequada als animals, cuidant-nos de l’alimentació , l’atenció veterinària i el manteniment de les instal·lacions on viuen.",
  "animalFocus": "cats&dogs",
  "shelter": [
    {
      "adress": "Torre d’en Bosch s/n, Gurb, a prop de l’ermita de Palau",
      "googleMapsLink": "https://maps.app.goo.gl/XhvwCZrFHCRvjdeK6",
      "phone": "638986301"
    }
  ],
  "adoptAnimalsURL": "https://www.instagram.com/protectora_osona/",
  "municipalityInscription": "Gurb",
  "municipality": "Gurb",
  "isMunicipal": true,
  "associativeInscriptionNumber": "11514",
  "isActive": true,
  "lastUpdate": "2025-04-10T00:00:00.000Z",
  "dateOfInscription": "1990-03-12T00:00:00.000Z",
  "socials": {
    "facebook": "https://www.facebook.com/ProtectoraAnimalsOsona",
    "instagram": "https://www.instagram.com/protectora_osona/"
  }
}